bob/__init__.py
bob/cli.py
bob-12.1.1.dist-info/LICENSE
bob-12.1.1.dist-info/METADATA
bob-12.1.1.dist-info/WHEEL
bob-12.1.1.dist-info/entry_points.txt
bob-12.1.1.dist-info/top_level.txt
bob-12.1.1.dist-info/RECORD
