Metadata-Version: 2.1
Name: bob
Version: 12.1.1
Summary: Bob is a free signal-processing and machine learning toolbox originally developed by the Biometrics group at Idiap Research Institute, in Switzerland.
Author-email: IDIAP Biometrics Group <biometric@idiap.ch>, Yannick Dayer <yannick.dayer@idiap.ch>
License: BSD 3-Clause License
Project-URL: documentation, https://www.idiap.ch/software/bob/docs/bob/bob/v12.1.1/
Project-URL: homepage, https://pypi.org/project/bob/
Project-URL: repository, https://gitlab.idiap.ch/bob/bob
Project-URL: changelog, https://gitlab.idiap.ch/bob/bob/-/releases
Keywords: bob,biometric recognition,evaluation
Classifier: Framework :: Bob
Classifier: Development Status :: 5 - Production/Stable
Classifier: Intended Audience :: Education
Classifier: Intended Audience :: Science/Research
Classifier: License :: OSI Approved :: BSD License
Classifier: Natural Language :: English
Classifier: Programming Language :: Python
Classifier: Programming Language :: Python :: 3
Classifier: Topic :: Scientific/Engineering :: Artificial Intelligence
Requires-Python: >=3.9
License-File: LICENSE
Requires-Dist: clapper ~=1.0
Requires-Dist: click ~=8.1
Requires-Dist: click-plugins ~=1.1
Provides-Extra: doc
Requires-Dist: sphinx ; extra == 'doc'
Requires-Dist: sphinx-rtd-theme ; extra == 'doc'
Requires-Dist: sphinx-autodoc-typehints ; extra == 'doc'
Requires-Dist: auto-intersphinx ; extra == 'doc'
Requires-Dist: sphinxcontrib-programoutput ; extra == 'doc'
Provides-Extra: qa
Requires-Dist: pre-commit ; extra == 'qa'
Provides-Extra: test
Requires-Dist: pytest ; extra == 'test'
Requires-Dist: pytest-cov ; extra == 'test'
Requires-Dist: coverage ; extra == 'test'
